llama_index/llms/digitalocean/gradientai/__init__.py
llama_index/llms/digitalocean/gradientai/base.py
llama_index_llms_digitalocean_gradientai-0.1.10.dist-info/licenses/LICENSE
llama_index_llms_digitalocean_gradientai-0.1.10.dist-info/METADATA
llama_index_llms_digitalocean_gradientai-0.1.10.dist-info/WHEEL
llama_index_llms_digitalocean_gradientai-0.1.10.dist-info/top_level.txt
llama_index_llms_digitalocean_gradientai-0.1.10.dist-info/RECORD
