Metadata-Version: 2.4
Name: llama-index-llms-digitalocean-gradientai
Version: 0.1.10
Summary: LlamaIndex integration for DigitalOcean Gradient AI
Home-page: https://github.com/bnarasimha21/llamaindex-digitalocean-gradientai
Author: Narasimha Badrinath
Author-email: Narasimha Badrinath <bnarasimha21@gmail.com>
License-Expression: MIT
Project-URL: Homepage, https://github.com/bnarasimha21/llamaindex-digitalocean-gradientai
Project-URL: Documentation, https://github.com/bnarasimha21/llamaindex-digitalocean-gradientai#readme
Project-URL: Repository, https://github.com/bnarasimha21/llamaindex-digitalocean-gradientai
Project-URL: Issues, https://github.com/bnarasimha21/llamaindex-digitalocean-gradientai/issues
Keywords: llamaindex,gradient,gradientai,llm,rag,digitalocean
Classifier: Development Status :: 3 - Alpha
Classifier: Intended Audience :: Developers
Classifier: Operating System :: OS Independent
Classifier: Programming Language :: Python :: 3
Classifier: Programming Language :: Python :: 3.8
Classifier: Programming Language :: Python :: 3.9
Classifier: Programming Language :: Python :: 3.10
Classifier: Programming Language :: Python :: 3.11
Classifier: Programming Language :: Python :: 3.12
Requires-Python: >=3.8
License-File: LICENSE
Requires-Dist: llama-index-core>=0.10.0
Requires-Dist: gradient>=3.8.0
Provides-Extra: dev
Requires-Dist: pytest>=7.0.0; extra == "dev"
Requires-Dist: pytest-asyncio>=0.21.0; extra == "dev"
Requires-Dist: pytest-cov>=4.0.0; extra == "dev"
Requires-Dist: black>=23.0.0; extra == "dev"
Requires-Dist: ruff>=0.1.0; extra == "dev"
Requires-Dist: mypy>=1.0.0; extra == "dev"
Requires-Dist: pre-commit>=3.0.0; extra == "dev"
Requires-Dist: python-dotenv>=1.0.0; extra == "dev"
Dynamic: author
Dynamic: home-page
Dynamic: license-file
Dynamic: requires-python
